aria2py/__init__.py
aria2py/client.py
aria2py/exceptions.py
aria2py/py.typed
aria2py/rpc_client.py
aria2py/utils.py
aria2py/models/__init__.py
aria2py/models/advanced.py
aria2py/models/base.py
aria2py/models/basic.py
aria2py/models/bt.py
aria2py/models/http.py
aria2py/models/metalink.py
aria2py/models/rpc.py
aria2py-0.1.2.dist-info/licenses/LICENSE
aria2py-0.1.2.dist-info/METADATA
aria2py-0.1.2.dist-info/WHEEL
aria2py-0.1.2.dist-info/top_level.txt
aria2py-0.1.2.dist-info/RECORD
