Metadata-Version: 2.4
Name: aria2py
Version: 0.1.2
Summary: A modern, type-safe Python wrapper for aria2c with improved UX.
Author: Omar Hanafy
License-Expression: MIT
Project-URL: Homepage, https://github.com/omar-hanafy/aria2py
Project-URL: Bug Tracker, https://github.com/omar-hanafy/aria2py/issues
Keywords: aria2,download,bittorrent,metalink,rpc
Classifier: Programming Language :: Python :: 3
Classifier: Operating System :: OS Independent
Classifier: Typing :: Typed
Requires-Python: >=3.9
License-File: LICENSE
Dynamic: license-file
